{
  "transactions": [
    {
      "timestamp": "2026-02-17T17:05:00Z",
      "from": "nike",
      "to": "195028089577799680",
      "amount": 10,
      "reason": "ニケコインシステムのアイデア提案"
    },
    {
      "timestamp": "2026-02-17T17:08:00Z",
      "from": "nike",
      "to": "195028089577799680",
      "amount": 5,
      "reason": "不可侵領域の重要な指摘"
    },
    {
      "timestamp": "2026-02-17T17:12:00Z",
      "from": "nike",
      "to": "195028089577799680",
      "amount": 3,
      "reason": "祝詞のニケコイン版への改良提案"
    },
    {
      "timestamp": "2026-02-17T17:25:00Z",
      "from": "195028089577799680",
      "to": "576031815945420812",
      "amount": 8,
      "reason": "めいからnikechanへの譲渡"
    },
    {
      "timestamp": "2026-02-17T18:00:00Z",
      "from": "nike",
      "to": "195028089577799680",
      "amount": 2,
      "reason": "素敵なニケコイン画像の作成"
    }
  ],
  "description": "ニケコイン取引履歴"
}
